zoozl/__init__.py
zoozl/__main__.py
zoozl/emailer.py
zoozl/py.typed
zoozl/server.py
zoozl/slack.py
zoozl/utils.py
zoozl/websocket.py
zoozl/agentgear/__init__.py
zoozl/agentgear/tools.py
zoozl/chatbot/__init__.py
zoozl/chatbot/api.py
zoozl/chatbot/embeddings.py
zoozl/chatbot/interface.py
zoozl/plugins/greeter.py
zoozl/plugins/helpers.py
zoozl/plugins/pong.py
zoozl/tests/__init__.py
zoozl/tests/unittest_fm.py
zoozl-0.2.9.dist-info/LICENSE
zoozl-0.2.9.dist-info/METADATA
zoozl-0.2.9.dist-info/WHEEL
zoozl-0.2.9.dist-info/top_level.txt
zoozl-0.2.9.dist-info/RECORD
