Metadata-Version: 2.1
Name: zoozl
Version: 0.2.9
Summary: Zoozl services for chatbots
Author-email: Juris Kaminskis <juris@kolumbs.net>
Project-URL: Repository, https://github.com/Kolumbs/zoozl
Requires-Python: <4,>=3.11.1
License-File: LICENSE
Requires-Dist: aiosmtpd<2,==1.4.6
Requires-Dist: membank<0.6,>=0.5.5
Requires-Dist: scipy<2,>=1.14.0
Requires-Dist: openai>=1.43.1
Requires-Dist: rapidfuzz<3,>=2.11.1
Requires-Dist: slack-sdk<4,>=3.33.1
